gmlutils/__init__.py
gmlutils/bayes.py
gmltutils-0.0.1.dist-info/LICENSE
gmltutils-0.0.1.dist-info/METADATA
gmltutils-0.0.1.dist-info/WHEEL
gmltutils-0.0.1.dist-info/top_level.txt
gmltutils-0.0.1.dist-info/RECORD
